Workbook

Sheet 📊 Dashboard
B2: FINMETRICS — Builder's Journal
B3: Borowy Consulting | Living Audit Log | How the System Was Built
B5: PHASE PROGRESS TRACKER
B6: Phase | C6: Description | D6: Status | E6: Hours Budget | F6: Hours Logged | G6: % Complete | H6: Target Date
B7: Phase 1 | C7: Foundation — Pipeline + React (10 tickers live) | D7: Not Started | E7: 120 | F7: =SUMIF(Journal!E:E,"Phase 1",Journal!D:D) -> 0 | G7: =IF(E7>0,F7/E7,0) -> 0
B8: Phase 2 | C8: Depth — Insight Layer + Power BI Reports | D8: Not Started | E8: 100 | F8: =SUMIF(Journal!E:E,"Phase 2",Journal!D:D) -> 0 | G8: =IF(E8>0,F8/E8,0) -> 0
B9: Phase 3 | C9: Scale — 230+ Companies + EDINET + Content Launch | D9: Not Started | E9: 160 | F9: =SUMIF(Journal!E:E,"Phase 3",Journal!D:D) -> 0 | G9: =IF(E9>0,F9/E9,0) -> 0
B10: Phase 4 | C10: Monetize — DART/TWSE + SaaS + Power BI Pack | D10: Not Started | E10: 140 | F10: =SUMIF(Journal!E:E,"Phase 4",Journal!D:D) -> 0 | G10: =IF(E10>0,F10/E10,0) -> 0
B13: HOURS BY COMPONENT
B14: Component | C14: Tag Used in Journal | D14: Hours Logged | E14: Sessions | F14: % of Total
B15: Pipeline / ETL | C15: Pipeline | D15: =SUMIF(Journal!F:F,C15,Journal!D:D) -> 0 | E15: =COUNTIF(Journal!F:F,C15) -> 0 | F15: =IF(SUM(Journal!D:D)>0,D15/SUM(Journal!D:D),0) -> 0
B16: Database / Schema | C16: Database | D16: =SUMIF(Journal!F:F,C16,Journal!D:D) -> 0 | E16: =COUNTIF(Journal!F:F,C16) -> 0 | F16: =IF(SUM(Journal!D:D)>0,D16/SUM(Journal!D:D),0) -> 0
B17: API (FastAPI) | C17: API | D17: =SUMIF(Journal!F:F,C17,Journal!D:D) -> 0 | E17: =COUNTIF(Journal!F:F,C17) -> 0 | F17: =IF(SUM(Journal!D:D)>0,D17/SUM(Journal!D:D),0) -> 0
B18: React Dashboard | C18: Dashboard | D18: =SUMIF(Journal!F:F,C18,Journal!D:D) -> 0 | E18: =COUNTIF(Journal!F:F,C18) -> 0 | F18: =IF(SUM(Journal!D:D)>0,D18/SUM(Journal!D:D),0) -> 0
B19: Power BI Reports | C19: PowerBI | D19: =SUMIF(Journal!F:F,C19,Journal!D:D) -> 0 | E19: =COUNTIF(Journal!F:F,C19) -> 0 | F19: =IF(SUM(Journal!D:D)>0,D19/SUM(Journal!D:D),0) -> 0
B20: Documentation / Spec | C20: Documentation | D20: =SUMIF(Journal!F:F,C20,Journal!D:D) -> 4 | E20: =COUNTIF(Journal!F:F,C20) -> 1 | F20: =IF(SUM(Journal!D:D)>0,D20/SUM(Journal!D:D),0) -> 1
B21: Research / Reading | C21: Research | D21: =SUMIF(Journal!F:F,C21,Journal!D:D) -> 0 | E21: =COUNTIF(Journal!F:F,C21) -> 0 | F21: =IF(SUM(Journal!D:D)>0,D21/SUM(Journal!D:D),0) -> 0
B22: Testing / Debugging | C22: Testing | D22: =SUMIF(Journal!F:F,C22,Journal!D:D) -> 0 | E22: =COUNTIF(Journal!F:F,C22) -> 0 | F22: =IF(SUM(Journal!D:D)>0,D22/SUM(Journal!D:D),0) -> 0
B23: TOTAL HOURS LOGGED | D23: =SUM(Journal!D:D) -> 4
B25: BUILD METRICS
B26: Metric | C26: Value | D26: Context
B27: Companies loaded | C27: =COUNTA(Companies!B:B)-1 -> 11 | D27: companies in database
B28: Metrics available | C28: =COUNTA(MetricStatus!B:B)-1 -> 76 | D28: of 75 public metrics
B29: Test suite coverage | C29: — | D29: % of pipeline tests passing
B30: Known gaps logged | C30: =COUNTA(Gaps!B:B)-1 -> 7 | D30: open gap entries
B31: Decisions logged | C31: =COUNTA(Decisions!B:B)-1 -> 6 | D31: architectural decisions
B32: Discoveries logged | C32: =COUNTA(Discoveries!B:B)-1 -> 4 | D32: unexpected data findings
B33: References read | C33: =COUNTA(Reading!B:B)-1 -> 6 | D33: papers, docs, articles

Sheet Journal
B2: BUILDER'S JOURNAL — Session Log
B3: One row per session. Date → Hours → Phase → Component → What happened → Decisions → Questions → Reading → Thoughts → Next intent.
B5: Date | C5: Session # | D5: Hours | E5: Phase | F5: Component | G5: Spec Section | H5: What Was Attempted / Completed | I5: What Broke / Surprised | J5: Decisions Made (with rationale) | K5: Questions Opened | L5: Next Session Intent
B6: 46175 | C6: 1 | D6: 4 | E6: Phase 0 | F6: Documentation | G6: All sections | H6: Completed FinMetrics Master Specification v1.0. Consolidated Roadmap v2, DataFramework, and ExpandedMetrics into single document. Added Section 7 Systems Analysis Framework — causal chains, stakeholder model, incentive layer. Expanded metric framework from 55 to 75. Defined 12 parked private metrics. Built complete Python pipeline scaffold with 31 passing tests. | I6: The document inventory had grown to 5+ active docs with overlapping content — alignment gaps identified across roadmap, data framework, and expanded metrics. Required full consolidation before systems framework could be added cleanly. | J6: Single master specification as single source of truth. Separate branded appendix for Borowy Consulting private framework. Living documents (Excel, code) stay separate. Retired 3 prior active documents into master. | K6: How will causal chains for remaining 71 metrics (beyond the 4 prototypes) be documented? Will they live in the Excel reference or the master spec? What is the right format for the Power BI Systems View (Page 7)? | L6: Begin Phase 1 pipeline build. Start with EDGAR connector testing — run diagnose_edgar.py against NVDA and TSM. Document findings in this journal before writing any ETL code.

Sheet Decisions
B2: ARCHITECTURAL DECISION LOG — Every significant choice, documented with rationale
B3: ADR # | C3: Date | D3: Phase | E3: Decision | F3: Context / Problem | G3: Rationale | H3: Alternatives Rejected | I3: Consequences
B4: ADR-001 | C4: 2026-06-02 | D4: Phase 1 | E4: PostgreSQL as primary database | F4: Need database supporting both pipeline writes and Power BI DirectQuery. Must scale from local dev to cloud without schema changes. | G4: Enterprise-grade, native Power BI connector, full SQL, JSONB for flags, TimescaleDB extension available for time-series optimization. | H4: SQLite (dev only, no PBI DirectQuery), MongoDB (no native SQL, limited PBI connector), Supabase (vendor lock-in on free tier). | I4: Power BI connects directly — no API layer needed for analyst reports. JSONB accounting_flags column stores flexible flag arrays. Denormalized flag_ boolean columns added for PBI filter performance.
B5: ADR-002 | C5: 2026-06-02 | D5: Phase 1 | E5: Canonical tag mapping as database table + in-memory resolver | F5: 5 filing systems use 5 different XBRL taxonomies. Same concept has different tag names. Within a single taxonomy, multiple valid synonym tags exist for the same concept. | G5: Seed mappings (~200 most common) ship with codebase. New tags discovered during pipeline runs logged and added to database without code changes. Priority ordering handles synonym disambiguation. | H5: Hardcoded tag lists per metric (brittle, hard to extend), External mapping service (dependency risk), Single canonical tag only (misses too many filings). | I5: tag_resolver.py loads all mappings at startup. Unresolved tags logged per session for review. Coverage % tracked in completeness_scores. New filing systems add new taxonomy sections incrementally.
B6: ADR-003 | C6: 2026-06-02 | D6: Phase 1 | E6: Period-average FX for P&L; period-end for B/S | F6: Companies report in JPY, EUR, KRW, TWD. All FinMetrics output must be USD-comparable. Conversion rate choice materially affects metric values. | G6: Standard financial reporting practice (FASB ASC 830 / IAS 21). Period-average eliminates single-date distortion for income statement items. Period-end reflects actual asset/liability value at reporting date. | H6: Single spot rate (distorts time-series), Annual average rate (loses quarterly precision), No conversion / local currency display (prevents cross-company comparison). | I6: fx_rates table stores daily rates per currency per source. Both rate types stored alongside value_usd in raw_facts for full audit trail. ECB and Fed H.10 as free sources.
B7: ADR-004 | C7: 2026-06-02 | D7: Phase 1 | E7: Diagnostic-first ETL workflow standard | F7: ETL errors are silent and compound. Wrong unit assumptions (monthly vs annual) produce plausible-looking numbers that are systematically wrong. Learned from HEMM IS_2012 era break and EAP EAPMED column misinterpretation. | G7: Mandatory diagnostic step before any ETL code prevents the most damaging failure mode: incorrect assumptions built into production code. Based on HEMM Section 8.4 workflow standard. | H7: Write ETL and fix errors later (reactive), Trust documentation without verification (naive), Add validation post-ETL (catches errors but too late). | I7: diagnose_edgar.py must be run and reviewed before any new company or data source ETL. Findings documented in ETL script header. This creates an audit trail from diagnosis to implementation.
B8: ADR-005 | C8: 2026-06-02 | D8: Phase 1 | E8: Master specification as single source of truth | F8: Five active documents with overlapping content created alignment gaps. Systems framework needed to integrate with roadmap, data model, metric definitions, and Power BI spec simultaneously. | G8: One document that all decisions reference. Eliminates drift. When something changes, it changes once. Retired documents preserved in Appendix C with content location map. | H8: Multiple specialized documents (drift risk), Wiki (version control harder), README-only (insufficient depth for this scope). | I8: Three documents retired into master. Living documents (Excel, code) stay separate as operational tools. Appendix A stays as Borowy Consulting branded document.

Sheet Discoveries
B2: DISCOVERY LOG — Unexpected findings in real data. The most valuable entries in this journal.
B3: When the data surprises you — document it here. This is where the real knowledge lives.
B4: Date | C4: Phase | D4: Company / Source | E4: What Was Found | F4: Why It Matters | G4: Action Taken / Impact on Methodology
B5: 2026-06-02 | C5: Phase 0 (HEMM) | D5: IPEDS / EDGAR general | E5: ETL era breaks are silent by default. The IS_2012 salary survey changed from monthly to annual values without documentation. Built pipeline assuming monthly × 9, producing numbers 9× too high that looked plausible. | F5: A single undocumented format change produced systematically wrong numbers across all institutions for multiple years. No error was thrown. The data looked reasonable. | G5: Established mandatory diagnostic-first workflow (ADR-004). diagnose_edgar.py runs before any ETL. Era changes now documented in script headers before code is written.
B6: 2026-06-02 | C6: Phase 0 (HEMM) | D6: IPEDS EAP survey | E6: EAPMED column name looks like "median" but actually means "medical school headcount." Named for a medical school subdivision, not a statistical measure. | F6: Column naming conventions in regulatory data are not self-documenting. Assumptions based on intuitive reading of names will fail. The only defense is reading the actual data dictionary. | G6: Added "Dictionary Review" as mandatory Step 1 of ETL workflow. Read minimum 2 non-consecutive years of dictionary before writing any code.

Sheet Gaps
B2: KNOWN GAPS REGISTRY — Every gap documented with workaround and resolution plan
B3: Gap ID | C3: Opened | D3: Table / Metric | E3: Description | F3: Workaround | G3: Resolution Plan | H3: Phase | I3: Status
B4: KG-HR-01 | C4: 2026-06-02 | D4: f_ipeds_hr_sal | E4: HEMM: 2000 gap year — no IPEDS salary file exists | F4: Document; no imputation | G4: Accept as structural gap in the data source | H4: Phase 0 | I4: Accepted
B5: KG-ED-01 | C5: 2026-06-02 | D5: EDGAR / tag_mappings | E5: Some companies use non-standard XBRL tags not in seed mapping. First seen when company uses custom extension taxonomy. | F5: Store raw fact with canonical_tag=NULL; log for review | G5: diagnose_edgar.py surfaces unresolved tags; add to tag_mappings table per new company | H5: Phase 1 | I5: Open
B6: KG-ED-02 | C6: 2026-06-02 | D6: metrics / Employees | E6: EntityNumberOfEmployees not consistently tagged across all EDGAR filers. Some companies report in MD&A text only. | F6: SPARSE_EMPLOYEES flag; metric set to NULL; text extraction Phase 3 | G6: Phase 3 text_extractor.py will attempt to find headcount in filing text | H6: Phase 3 | I6: Deferred
B7: KG-ED-03 | C7: 2026-06-02 | D7: text_facts / Customer Conc | E7: Customer concentration not XBRL-tagged. Requires 10-K text extraction with pattern matching. Confidence varies by disclosure format. | F7: TEXT_LOW_CONFIDENCE or TEXT_NOT_DISCLOSED flags; metric NULL where undisclosed | G7: text_extractor.py Phase 2-3. Confidence scoring. Raw excerpt stored for audit. | H7: Phase 2-3 | I7: Deferred
B8: KG-ED-04 | C8: 2026-06-02 | D8: sector_book_to_bill | E8: Company-level book-to-bill not standardized in XBRL. SEMI publishes sector-level only. Company-level requires earnings call parsing. | F8: Use SEMI sector data Phase 2. Flag BTB_SECTOR_ONLY. | G8: Phase 3: per-company parsing for AMAT, LRCX, KLAC, TEL who disclose backlog. | H8: Phase 3 | I8: Deferred
B9: KG-FX-01 | C9: 2026-06-02 | D9: fx_rates | E9: ECB/Fed rates may not be available for all dates (holidays, weekends). Exact date miss for period-end B/S conversion. | F9: Fallback: search ±7 days for nearest rate. Log warning when fallback used. | G9: Accept as operational gap. Document fallback in fx_converter.py | H9: Phase 1 | I9: Accepted

Sheet Reading
B2: READING LOG — Papers, documentation, articles. What you read, when, and what it changed.
B3: Date | C3: Title / Source | D3: Author / URL | E3: Type | F3: Relevance | G3: Key Takeaways & Impact on Build
B4: 2026-06-02 | C4: SEC EDGAR XBRL API Documentation | D4: data.sec.gov/api | E4: Technical | F4: Pipeline | G4: CompanyFacts endpoint returns all filed XBRL facts in one JSON call. User-Agent header required — 403 without it. 10 req/sec rate limit across all EDGAR domains. CIK must be zero-padded to 10 digits.
B5: 2026-06-02 | C5: IFRS vs US GAAP: The Basics — EY Annual Guide | D5: ey.com/en_us/assurance/ifrs | E5: Technical | F5: Normalization | G5: LIFO prohibited under IFRS. Development costs capitalized under IAS 38 if 6 criteria met. IFRS 16 vs ASC 842 lease treatment difference produces EBITDA gap that must be adjusted for peer comparison. Asset revaluation under IAS 16 affects return ratios.
B6: 2026-06-02 | C6: IPEDS Data Center — Survey Documentation | D6: nces.ed.gov/ipeds/datacenter | E6: Technical | F6: HEMM / Phase 0 | G6: HEMM origin reference. Dictionary review before ETL is mandatory — column names are not self-documenting (see EAPMED discovery). Era breaks must be confirmed against actual data schema, not assumed from documentation.
B7: 2026-06-02 | C7: SEMI Industry Book-to-Bill Reports | D7: semi.org/en/products-services/market-data | E7: Industry Data | F7: Semiconductor | G7: Monthly publication of North American semiconductor book-to-bill ratio. Free download. Historical data available. Leading indicator of semiconductor demand direction 1-3 quarters ahead.
B8: 2026-06-02 | C8: Thinking in Systems — Donella Meadows | D8: Chelsea Green Publishing, 2008 | E8: Book | F8: Systems Framework | G8: Foundational text for systems thinking framework in Section 7. Reinforcing vs balancing loops. Stock and flow diagrams. Leverage points — where small changes produce large effects. Time delays as source of most business decision errors. The bathtub metaphor for stocks.

Sheet Companies
B2: COMPANY TRACKER — Pipeline load status per company
B3: Ticker | C3: Company Name | D3: Sub-Sector | E3: Filing System | F3: Phase | G3: Date Loaded | H3: Completeness % | I3: Status
B4: NVDA | C4: Nvidia Corporation | D4: Fabless | E4: EDGAR | F4: Phase 1 | I4: Planned
B5: AAPL | C5: Apple Inc. | D5: Consumer Tech / Semi customer | E5: EDGAR | F5: Phase 1 | I5: Planned
B6: MSFT | C6: Microsoft Corporation | D6: Information Technology benchmark | E6: EDGAR | F6: Phase 1 | I6: Planned
B7: AMZN | C7: Amazon.com Inc. | D7: Consumer Disc benchmark | E7: EDGAR | F7: Phase 1 | I7: Planned
B8: TSM | C8: Taiwan Semiconductor (ADR) | D8: Foundry | E8: EDGAR 20-F | F8: Phase 1 | I8: Planned
B9: ASML | C9: ASML Holding NV (ADR) | D9: Equipment | E9: EDGAR 20-F | F9: Phase 1 | I9: Planned
B10: AMD | C10: Advanced Micro Devices | D10: Fabless | E10: EDGAR | F10: Phase 1 | I10: Planned
B11: INTC | C11: Intel Corporation | D11: IDM | E11: EDGAR | F11: Phase 1 | I11: Planned
B12: AMAT | C12: Applied Materials Inc. | D12: Equipment | E12: EDGAR | F12: Phase 1 | I12: Planned
B13: JPM | C13: JPMorgan Chase & Co. | D13: Financials benchmark | E13: EDGAR | F13: Phase 1 | I13: Planned

Sheet MetricStatus
B2: METRIC STATUS — Tag mapping and calculation status per metric
B3: Metric | C3: Category | D3: Phase | E3: Tag Mapped | F3: Calc Implemented | G3: Notes
B4: Common Shares | C4: Growth | D4: 1 | E4: No | F4: No
B5: Employee Growth | C5: Growth | D5: 1 | E5: No | F5: No
B6: Employees | C6: Growth | D6: 1 | E6: No | F6: No
B7: Market Capitalization | C7: Growth | D7: 1 | E7: No | F7: No
B8: R&D Margin | C8: Growth | D8: 1 | E8: No | F8: No
B9: R&D Ratio | C9: Growth | D9: 1 | E9: No | F9: No
B10: R&D To COGS Ratio | C10: Growth | D10: 1 | E10: No | F10: No
B11: Revenue | C11: Growth | D11: 1 | E11: No | F11: No
B12: Revenue Growth | C12: Growth | D12: 1 | E12: No | F12: No
B13: Revenue Growth TTM | C13: Growth | D13: 1 | E13: No | F13: No
B14: Revenue TTM | C14: Growth | D14: 1 | E14: No | F14: No
B15: SG&A Margin | C15: Growth | D15: 1 | E15: No | F15: No
... B78: Days Cash On Hand | C78: Cash Flow Quality | D78: 1 | E78: No | F78: No
